[{"data":"זרעית, שומרה","alertDate":"2026-04-07T12:04:06.000Z","time":1775563446,"threat":0,"isDrill":false},{"data":"אביבים","alertDate":"2026-04-07T11:55:50.000Z","time":1775562950,"threat":0,"isDrill":false},{"data":"יראון","alertDate":"2026-04-07T11:55:41.000Z","time":1775562941,"threat":0,"isDrill":false},{"data":"מלכיה","alertDate":"2026-04-07T11:55:40.000Z","time":1775562940,"threat":0,"isDrill":false},{"data":"אביבים","alertDate":"2026-04-07T11:49:03.000Z","time":1775562543,"threat":0,"isDrill":false},{"data":"מטולה","alertDate":"2026-04-07T11:30:50.000Z","time":1775561450,"threat":0,"isDrill":false},{"data":"משגב עם","alertDate":"2026-04-07T10:34:38.000Z","time":1775558078,"threat":0,"isDrill":false},{"data":"מטולה, ע'ג'ר","alertDate":"2026-04-07T10:24:03.000Z","time":1775557443,"threat":5,"isDrill":false},{"data":"מרגליות","alertDate":"2026-04-07T10:23:27.000Z","time":1775557407,"threat":5,"isDrill":false},{"data":"בית העמק, נס עמים, נתיב השיירה, עברון, לוחמי הגטאות, מזרעה, רגבה","alertDate":"2026-04-07T10:21:59.000Z","time":1775557319,"threat":0,"isDrill":false},{"data":"טמרה","alertDate":"2026-04-07T10:21:45.000Z","time":1775557305,"threat":0,"isDrill":false},{"data":"בוסתן הגליל, עכו - רמות ים, עכו, שמרת","alertDate":"2026-04-07T10:21:19.000Z","time":1775557279,"threat":0,"isDrill":false},{"data":"קרני שומרון, אייל, חרות, טירה, כוכב יאיר - צור יגאל, כפר הס, משמרת, צור יצחק, צור נתן, רמת הכובש, געש, חרוצים, עמנואל, הר ברכה, חוות גלעד, יצהר, כפר תפוח, סלעית, קדומים, רחלים, אביתר, אריאל, חוות נוף אב\"י, נופי נחמיה","alertDate":"2026-04-07T10:07:16.000Z","time":1775556436,"threat":0,"isDrill":false},{"data":"כפר שמואל, כרמי יוסף, לטרון, מזכרת בתיה, מיני ישראל - נחשון, מסילת ציון, משמר איילון, משמר דוד, נאות קדומים, נווה שלום, נחשון, נען, נצר חזני, סתריה, עזריה, פדיה, פתחיה, צלפון, קריית עקרון, רטורנו - גבעת שמש, רמות מאיר, תעוז, תרום, כפר האורנים, מודיעין - ישפרו סנטר, נילי, חוות מגנזי","alertDate":"2026-04-07T10:07:04.000Z","time":1775556424,"threat":0,"isDrill":false},{"data":"חוות שוביאל, גיבתון, גמזו, גן שלמה, חשמונאים, כפר דניאל, כפר רות, לפיד, מבוא חורון, מבוא מודיעים, מודיעין - ליגד סנטר, מודיעין מכבים רעות, נוף איילון, שעלבים, רחובות, שילת, אזור תעשייה נשר - רמלה, ישרש, מצליח, בני ציון, בית חשמונאי, בית עוזיאל, בקוע, גבעת ברנר, גזר, גיזו, גני הדר, גני יוחנן, הראל, חולדה, טל שחר, יד רמב''ם, יסודות, יציץ, כפר אוריה, כפר ביל''ו, כפר בן נון","alertDate":"2026-04-07T10:07:03.000Z","time":1775556423,"threat":0,"isDrill":false},{"data":"בצרה, צופים, שפיים","alertDate":"2026-04-07T10:06:45.000Z","time":1775556405,"threat":0,"isDrill":false},{"data":"רעננה, בית ברל, גן חיים, ניר אליהו, צופית, שדה ורבורג, אלפי מנשה, ארסוף, חוות יאיר, יקיר, נופים, רבבה, רשפון, תל אביב - דרום העיר ויפו, תל אביב - מזרח, תל אביב - מרכז העיר, תל אביב - עבר הירקון, אור יהודה, אזור, בני ברק, בת ים, גבעת השלושה, גבעת חן, גבעת שמואל, גבעתיים, גת רימון, הרצליה - מערב, הרצליה - מרכז וגליל ים, חולון, יהוד מונוסון, כפר סירקין, כפר שמריהו, מעש, מקווה ישראל, נצר סרני, סביון, פארק אריאל שרון, פארק תעשיות פלמחים, פלמחים, פתח תקווה, קריית אונו, ראשון לציון - מזרח, ראשון לציון - מערב, רמת גן - מזרח, רמת גן - מערב, רמת השרון, אורנית, אחיסמך, אירוס, אלישמע, אלעד, באר יעקב, בארות יצחק, בית חנן, בית עובד, בן שמן, בני עטרות, ג'לג'וליה, גבעת כ''ח, גינתון, גן שורק, גני עם, גני תקווה, הוד השרון, חגור, חורשים, ירחיב, ירקונה, כפר ברא, כפר מל''ל, כפר נוער בן שמן, כפר סבא, כפר קאסם, לוד, מגשימים, מזור, מתן, נווה ימין, נווה ירק, נופך, נחלים, נחשונים, נטעים, ניר צבי, נירית, נס ציונה, עדנים, עיינות, עינת, ראש העין, רינתיה, רמות השבים, רמלה, שדי חמד, תחנת רכבת ראש העין, תעשיון צריפין, אזור תעשייה חבל מודיעין שוהם, אחיעזר, אלקנה, בית דגן, בית נחמיה, בית עריף, ברקן, ברקת, זיתן, חדיד, חמד, טירת יהודה, יגל, כפר חב''ד, כפר טרומן, משמר השבעה, עץ אפרים, צפריה, קריית נטפים, שוהם, שערי תקווה, אזור תעשייה אריאל, אזור תעשייה ברקן, בית אריה, בית עלמין מורשה, ברוכין, חוות אביחי, מסוף אורנית, עלי זהב - לשם, פדואל, אזור תעשייה אפק ולב הארץ, איירפורט סיטי, גנות, דורות עילית, חוות עולם חסד, חוות צרידה, חוות שחרית, מרכז אזורי דרום השרון, מתחם גלילות, מתחם פי גלילות, עופרים","alertDate":"2026-04-07T10:06:35.000Z","time":1775556395,"threat":0,"isDrill":false},{"data":"מנרה, מרגליות, קריית שמונה","alertDate":"2026-04-07T10:06:16.000Z","time":1775556376,"threat":0,"isDrill":false},{"data":"חצור הגלילית, ראש פינה","alertDate":"2026-04-07T10:02:04.000Z","time":1775556124,"threat":0,"isDrill":false},{"data":"צפת - עיר","alertDate":"2026-04-07T10:01:22.000Z","time":1775556082,"threat":0,"isDrill":false},{"data":"קריית שמונה","alertDate":"2026-04-07T09:17:30.000Z","time":1775553450,"threat":0,"isDrill":false},{"data":"חורפיש, פקיעין","alertDate":"2026-04-07T09:09:08.000Z","time":1775552948,"threat":0,"isDrill":false},{"data":"בית ג'אן","alertDate":"2026-04-07T09:08:39.000Z","time":1775552919,"threat":0,"isDrill":false},{"data":"משגב עם","alertDate":"2026-04-07T08:58:19.000Z","time":1775552299,"threat":0,"isDrill":false},{"data":"איזור תעשייה מילואות צפון, בצת, לימן, מצובה, ראש הנקרה, שלומי","alertDate":"2026-04-07T08:53:54.000Z","time":1775552034,"threat":0,"isDrill":false},{"data":"נהריה","alertDate":"2026-04-07T08:53:47.000Z","time":1775552027,"threat":0,"isDrill":false},{"data":"מנרה","alertDate":"2026-04-07T08:20:15.000Z","time":1775550015,"threat":0,"isDrill":false},{"data":"מרגליות","alertDate":"2026-04-07T08:17:44.000Z","time":1775549864,"threat":0,"isDrill":false},{"data":"דישון","alertDate":"2026-04-07T07:57:23.000Z","time":1775548643,"threat":0,"isDrill":false},{"data":"מלכיה","alertDate":"2026-04-07T07:57:19.000Z","time":1775548639,"threat":0,"isDrill":false},{"data":"רמות נפתלי","alertDate":"2026-04-07T07:57:09.000Z","time":1775548629,"threat":0,"isDrill":false},{"data":"משגב עם","alertDate":"2026-04-07T07:40:54.000Z","time":1775547654,"threat":0,"isDrill":false},{"data":"משגב עם","alertDate":"2026-04-07T07:38:35.000Z","time":1775547515,"threat":0,"isDrill":false},{"data":"מעונה, חוסן, כפר ורדים, מעלות תרשיחא, ינוח ג'ת, כסרא סמיע, מגדל תפן, פקיעין החדשה, צוריאל","alertDate":"2026-04-07T07:31:16.000Z","time":1775547076,"threat":0,"isDrill":false},{"data":"מג'דל כרום","alertDate":"2026-04-07T07:31:08.000Z","time":1775547068,"threat":0,"isDrill":false},{"data":"בענה, דיר אל-אסד, כרמיאל, לבון","alertDate":"2026-04-07T07:31:05.000Z","time":1775547065,"threat":0,"isDrill":false},{"data":"אביבים, יראון","alertDate":"2026-04-07T07:16:01.000Z","time":1775546161,"threat":0,"isDrill":false},{"data":"אבן מנחם","alertDate":"2026-04-07T07:08:24.000Z","time":1775545704,"threat":0,"isDrill":false},{"data":"זרעית, שומרה","alertDate":"2026-04-07T07:08:14.000Z","time":1775545694,"threat":0,"isDrill":false},{"data":"אבן מנחם, זרעית, שומרה","alertDate":"2026-04-07T06:54:53.000Z","time":1775544893,"threat":0,"isDrill":false},{"data":"אבן מנחם, זרעית, שומרה","alertDate":"2026-04-07T06:28:28.000Z","time":1775543308,"threat":0,"isDrill":false},{"data":"בית חנן, גיבתון, גן שלמה, מודיעין - ליגד סנטר, נצר סרני, רחובות, אזור תעשייה נשר - רמלה, אירוס, בית עובד, ישרש, מצליח, נס ציונה, עיינות, רמלה, גבעת ברנר, גני הדר, יד רמב''ם, כפר ביל''ו, נען, סתריה, עזריה","alertDate":"2026-04-07T06:11:09.000Z","time":1775542269,"threat":0,"isDrill":false},{"data":"אילות, אילת, אזור תעשייה שחורת","alertDate":"2026-04-07T06:10:59.000Z","time":1775542259,"threat":0,"isDrill":false},{"data":"גמזו, חשמונאים, כפר דניאל, מבוא מודיעים, מודיעין עילית, אחיסמך, באר יעקב, בן שמן, גינתון, כפר נוער בן שמן, לוד, ניר צבי, בית נחמיה, חדיד, כפר טרומן, נאות קדומים, מעלה לבונה, נווה צוף, נחליאל, נילי, נעלה, עטרת, גופנה, חוות מגנזי, חוות נווה צוף, חוות עולם חסד, יבוא דודי, כרם רעים, מכינת אלישע, נריה, עופרים, שדה אפרים","alertDate":"2026-04-07T06:10:35.000Z","time":1775542235,"threat":0,"isDrill":false},{"data":"בת ים, פארק תעשיות פלמחים, ראשון לציון - מזרח, ראשון לציון - מערב, פלמחים, חולון, גן שורק, נטעים, תעשיון צריפין, אזור תעשייה חבל מודיעין שוהם, אחיעזר, בית דגן, בית עריף, ברקת, זיתן, טירת יהודה, יגל, כפר חב''ד, משמר השבעה, צפריה, שוהם, איירפורט סיטי","alertDate":"2026-04-07T06:10:25.000Z","time":1775542225,"threat":0,"isDrill":false},{"data":"אליפז ומכרות תמנע, באר אורה, נתניה - מזרח, נתניה - מערב, גאולים, פרדסיה, צור משה, קלנסווה, שער אפרים, אבני חפץ, אזור תעשייה כפר יונה, בארותיים, בורגתה, גנות הדר, יד חנה, ינוב, כפר יונה, נורדיה, ניצני עוז, עולש, ענב, תנובות, חוות אלחי, חומש","alertDate":"2026-04-07T06:10:22.000Z","time":1775542222,"threat":0,"isDrill":false},{"data":"תל אביב - דרום העיר ויפו, תל אביב - מזרח, תל אביב - מרכז העיר, תל אביב - עבר הירקון, אור יהודה, אזור, בני ברק, גבעת השלושה, גבעת חן, גבעת שמואל, גבעתיים, גת רימון, הרצליה - מערב, הרצליה - מרכז וגליל ים, יהוד מונוסון, כפר סירקין, כפר שמריהו, מעש, מקווה ישראל, סביון, פארק אריאל שרון, פתח תקווה, קריית אונו, רמת גן - מזרח, רמת גן - מערב, רמת השרון, רעננה, אורנית, אייל, אלישמע, אלעד, בארות יצחק, בית ברל, בני דרור, בני עטרות, ג'לג'וליה, גבעת כ''ח, גן חיים, גני עם, גני תקווה, הוד השרון, חגור, חורשים, חרות, טייבה, טירה, יעבץ, יעף, ירחיב, ירקונה, כוכב יאיר - צור יגאל, כפר ברא, כפר הס, כפר מל''ל, כפר סבא, כפר עבודה, כפר קאסם, מגשימים, מזור, משמרת, מתן, נווה ימין, נווה ירק, נופך, נחלים, נחשונים, ניר אליהו, נירית, עדנים, עזריאל, עין ורד, עין שריד, עינת, פורת, צופית, צור יצחק, צור נתן, קדימה צורן, ראש העין, רינתיה, רמות השבים, רמת הכובש, שדה ורבורג, שדי חמד, תחנת רכבת ראש העין, תל מונד, אבן יהודה, אודים, אלפי מנשה, אלקנה, ארסוף, בית יהושע, בני ציון, בצרה, ברקן, געש, חוות יאיר, חמד, חרוצים, יקום, יקיר, כפר נטר, מכון וינגייט, נופים, עמנואל, עץ אפרים, צופים, קריית נטפים, קרני שומרון, רבבה, רשפון, שערי תקווה, שפיים, תל יצחק, אזור תעשייה אריאל, אזור תעשייה בראון, אזור תעשייה ברקן, בית אריה, בית עלמין מורשה, ברוכין, הר ברכה, חוות אביחי, חוות גלעד, יצהר, כפר תפוח, מסוף אורנית, סלעית, עלי זהב - לשם, פדואל, קדומים, שבי שומרון, אזור תעשייה אפק ולב הארץ, אריאל, גנות, דורות עילית, חוות נוף אב\"י, חוות צרידה, חוות שוביאל, חוות שחרית, מרכז אזורי דרום השרון, מתחם גלילות, מתחם פי גלילות","alertDate":"2026-04-07T06:10:20.000Z","time":1775542220,"threat":0,"isDrill":false},{"data":"גרופית, יטבתה, לוטן, סמר, קטורה, שחרות","alertDate":"2026-04-07T06:07:23.000Z","time":1775542043,"threat":0,"isDrill":false},{"data":"אליפז ומכרות תמנע, באר אורה","alertDate":"2026-04-07T06:07:21.000Z","time":1775542041,"threat":0,"isDrill":false},{"data":"אילות, אילת, אזור תעשייה שחורת","alertDate":"2026-04-07T06:07:20.000Z","time":1775542040,"threat":0,"isDrill":false},{"data":"בצת, שלומי","alertDate":"2026-04-07T06:01:05.000Z","time":1775541665,"threat":0,"isDrill":false},{"data":"בצת","alertDate":"2026-04-07T05:46:53.000Z","time":1775540813,"threat":0,"isDrill":false},{"data":"שלומי","alertDate":"2026-04-07T05:46:45.000Z","time":1775540805,"threat":0,"isDrill":false},{"data":"מטולה","alertDate":"2026-04-07T05:41:39.000Z","time":1775540499,"threat":0,"isDrill":false},{"data":"כפר גלעדי, מטולה","alertDate":"2026-04-07T05:38:43.000Z","time":1775540323,"threat":0,"isDrill":false},{"data":"מטולה","alertDate":"2026-04-07T05:05:01.000Z","time":1775538301,"threat":0,"isDrill":false},{"data":"כפר גלעדי, תל חי","alertDate":"2026-04-07T05:04:50.000Z","time":1775538290,"threat":0,"isDrill":false},{"data":"מנרה, מרגליות, קריית שמונה","alertDate":"2026-04-07T05:04:48.000Z","time":1775538288,"threat":0,"isDrill":false},{"data":"כפר גלעדי, מטולה, משגב עם","alertDate":"2026-04-07T03:55:21.000Z","time":1775534121,"threat":0,"isDrill":false},{"data":"קריית שמונה","alertDate":"2026-04-07T03:55:10.000Z","time":1775534110,"threat":0,"isDrill":false},{"data":"מרעית","alertDate":"2026-04-07T00:32:29.000Z","time":1775521949,"threat":0,"isDrill":false},{"data":"טללים, אל סייד","alertDate":"2026-04-07T00:31:07.000Z","time":1775521867,"threat":0,"isDrill":false},{"data":"צאלים","alertDate":"2026-04-07T00:30:57.000Z","time":1775521857,"threat":0,"isDrill":false},{"data":"באר שבע - דרום, באר שבע - מזרח, באר שבע - מערב, באר שבע - צפון, אבו קרינאת, אזור תעשייה דימונה, אל פורעה, דימונה, כסייפה, ערערה בנגב, קסר א-סר, נבטים, סעווה, שגב שלום, תל שבע, ביר הדאג', חצרים, משאבי שדה, עומר, רביבים, רתמים, אבו תלול, אום בטין, ואדי אל נעם דרום","alertDate":"2026-04-07T00:30:56.000Z","time":1775521856,"threat":0,"isDrill":false},{"data":"חוף זיקים","alertDate":"2026-04-07T00:30:53.000Z","time":1775521853,"threat":0,"isDrill":false},{"data":"מטולה","alertDate":"2026-04-06T23:39:40.000Z","time":1775518780,"threat":0,"isDrill":false},{"data":"מטולה","alertDate":"2026-04-06T21:42:15.000Z","time":1775511735,"threat":0,"isDrill":false},{"data":"כפר יובל","alertDate":"2026-04-06T21:42:04.000Z","time":1775511724,"threat":0,"isDrill":false},{"data":"משגב עם","alertDate":"2026-04-06T20:56:26.000Z","time":1775508986,"threat":0,"isDrill":false},{"data":"מרגליות","alertDate":"2026-04-06T17:36:15.000Z","time":1775496975,"threat":0,"isDrill":false},{"data":"גורן, גורנות הגליל","alertDate":"2026-04-06T17:27:15.000Z","time":1775496435,"threat":0,"isDrill":false},{"data":"יראון","alertDate":"2026-04-06T16:40:23.000Z","time":1775493623,"threat":5,"isDrill":false},{"data":"יפתח, רמות נפתלי","alertDate":"2026-04-06T16:39:59.000Z","time":1775493599,"threat":5,"isDrill":false},{"data":"דישון, מלכיה","alertDate":"2026-04-06T16:39:55.000Z","time":1775493595,"threat":5,"isDrill":false},{"data":"משגב עם","alertDate":"2026-04-06T16:39:39.000Z","time":1775493579,"threat":5,"isDrill":false},{"data":"אביבים","alertDate":"2026-04-06T16:39:34.000Z","time":1775493574,"threat":5,"isDrill":false},{"data":"מרגליות","alertDate":"2026-04-06T16:38:43.000Z","time":1775493523,"threat":5,"isDrill":false},{"data":"בית הלל","alertDate":"2026-04-06T16:07:29.000Z","time":1775491649,"threat":0,"isDrill":false},{"data":"קריית שמונה","alertDate":"2026-04-06T16:07:22.000Z","time":1775491642,"threat":0,"isDrill":false},{"data":"כפר בלום","alertDate":"2026-04-06T16:07:18.000Z","time":1775491638,"threat":0,"isDrill":false},{"data":"ראש הנקרה","alertDate":"2026-04-06T15:47:33.000Z","time":1775490453,"threat":5,"isDrill":false},{"data":"בצת","alertDate":"2026-04-06T15:47:29.000Z","time":1775490449,"threat":5,"isDrill":false},{"data":"חניתה, שלומי","alertDate":"2026-04-06T15:45:46.000Z","time":1775490346,"threat":5,"isDrill":false},{"data":"יראון","alertDate":"2026-04-06T15:40:30.000Z","time":1775490030,"threat":0,"isDrill":false},{"data":"יערה, ערב אל עראמשה","alertDate":"2026-04-06T15:37:00.000Z","time":1775489820,"threat":5,"isDrill":false},{"data":"חניתה","alertDate":"2026-04-06T15:34:33.000Z","time":1775489673,"threat":5,"isDrill":false},{"data":"אדמית, ערב אל עראמשה","alertDate":"2026-04-06T15:33:55.000Z","time":1775489635,"threat":5,"isDrill":false},{"data":"כפר גלעדי","alertDate":"2026-04-06T15:28:21.000Z","time":1775489301,"threat":5,"isDrill":false},{"data":"מרגליות, משגב עם, קריית שמונה","alertDate":"2026-04-06T15:28:19.000Z","time":1775489299,"threat":5,"isDrill":false},{"data":"מרגליות","alertDate":"2026-04-06T15:17:11.000Z","time":1775488631,"threat":5,"isDrill":false},{"data":"מנרה","alertDate":"2026-04-06T15:16:45.000Z","time":1775488605,"threat":5,"isDrill":false},{"data":"יפתח, מלכיה, רמות נפתלי","alertDate":"2026-04-06T15:04:24.000Z","time":1775487864,"threat":5,"isDrill":false},{"data":"מרגליות","alertDate":"2026-04-06T14:39:03.000Z","time":1775486343,"threat":0,"isDrill":false},{"data":"משגב עם","alertDate":"2026-04-06T14:38:59.000Z","time":1775486339,"threat":0,"isDrill":false},{"data":"משגב עם, תל חי","alertDate":"2026-04-06T14:37:02.000Z","time":1775486222,"threat":5,"isDrill":false},{"data":"ע'ג'ר","alertDate":"2026-04-06T14:36:28.000Z","time":1775486188,"threat":5,"isDrill":false},{"data":"כפר יובל","alertDate":"2026-04-06T14:36:11.000Z","time":1775486171,"threat":5,"isDrill":false},{"data":"כפר גלעדי","alertDate":"2026-04-06T14:36:05.000Z","time":1775486165,"threat":5,"isDrill":false},{"data":"מטולה","alertDate":"2026-04-06T14:35:58.000Z","time":1775486158,"threat":0,"isDrill":false},{"data":"מרגליות","alertDate":"2026-04-06T14:29:10.000Z","time":1775485750,"threat":0,"isDrill":false},{"data":"מרגליות, משגב עם","alertDate":"2026-04-06T14:13:56.000Z","time":1775484836,"threat":0,"isDrill":false},{"data":"קריית שמונה","alertDate":"2026-04-06T13:57:29.000Z","time":1775483849,"threat":0,"isDrill":false},{"data":"אזור תעשייה רמת דלתון, ברעם, ג'ש - גוש חלב, כרם בן זמרה, ריחאנייה","alertDate":"2026-04-06T13:49:18.000Z","time":1775483358,"threat":0,"isDrill":false},{"data":"קדיתא","alertDate":"2026-04-06T13:49:12.000Z","time":1775483352,"threat":0,"isDrill":false},{"data":"גדות","alertDate":"2026-04-06T13:43:56.000Z","time":1775483036,"threat":0,"isDrill":false},{"data":"קצרין - אזור תעשייה, קצרין","alertDate":"2026-04-06T13:43:27.000Z","time":1775483007,"threat":0,"isDrill":false},{"data":"מנרה","alertDate":"2026-04-06T13:18:52.000Z","time":1775481532,"threat":5,"isDrill":false},{"data":"כפר גלעדי, קריית שמונה, תל חי","alertDate":"2026-04-06T13:16:57.000Z","time":1775481417,"threat":5,"isDrill":false},{"data":"מרגליות","alertDate":"2026-04-06T13:16:53.000Z","time":1775481413,"threat":5,"isDrill":false},{"data":"אבני חפץ, ורד יריחו, מבואות יריחו, נעמה, ענב, בית חגלה, חומש","alertDate":"2026-04-06T13:00:03.000Z","time":1775480403,"threat":0,"isDrill":false},{"data":"אחווה, כפר אחים","alertDate":"2026-04-06T12:58:56.000Z","time":1775480336,"threat":0,"isDrill":false},{"data":"אזור תעשייה עד הלום, אשדוד - א,ב,ד,ה, אשדוד - ג,ו,ז, אשדוד - ח,ט,י,יג,יד,טז, אשדוד -יא,יב,טו,יז,מרינה,סיט, אורות, בני ראם, כפר הרי''ף וצומת ראם, רבדים, תלמי יחיאל, אזור תעשייה רבדים, גן יבנה, חצב, חצור, אמונים, בית עזרא, גבעתי, ניצן, עזר, עזריקם, שדה עוזיהו, שתולים, פארק תעשייה ראם","alertDate":"2026-04-06T12:58:25.000Z","time":1775480305,"threat":0,"isDrill":false},{"data":"נתניה - מזרח, נתניה - מערב, בני דרור, חרות, קדימה צורן, תל מונד, אבן יהודה, אודים, בית יהושע, בני ציון, געש, חרוצים, יקום, כפר נטר, מכון וינגייט, תל יצחק","alertDate":"2026-04-06T12:58:19.000Z","time":1775480299,"threat":0,"isDrill":false},{"data":"בית חלקיה, יד בנימין, גני טל, חפץ חיים, ביצרון, בני עי''ש","alertDate":"2026-04-06T12:58:00.000Z","time":1775480280,"threat":0,"isDrill":false},{"data":"מתחם פי גלילות","alertDate":"2026-04-06T12:57:46.000Z","time":1775480266,"threat":0,"isDrill":false},{"data":"אשדוד - איזור תעשייה צפוני, בני דרום, ניר גלים, גדרה, קדרון, אזור תעשייה כנות, גבעת וושינגטון, גן הדרום, כנות, כפר אביב, כרם ביבנה, מישר, משגב דב, מתחם בני דרום, נווה מבטח, עשרת, קבוצת יבנה, אזור תעשייה גדרה, כוכב יאיר - צור יגאל, ניר אליהו","alertDate":"2026-04-06T12:57:40.000Z","time":1775480260,"threat":0,"isDrill":false},{"data":"שדמה, כפר מרדכי, בניה, בית אלעזרי, בן זכאי, בית גמליאל, יבנה, מעון צופיה","alertDate":"2026-04-06T12:57:38.000Z","time":1775480258,"threat":0,"isDrill":false},{"data":"מעלה החמישה, אזור תעשייה שער בנימין, מעלה מכמש, חוות מלכיאל, חוות נחלת צבי, מצפה דני, ירושלים - אזור תעשייה עטרות, ירושלים - כפר עקב, תל אביב - מרכז העיר, תל אביב - עבר הירקון, מבוא חורון, רמת השרון, הר אדר, כפר מל''ל, כפר סבא, בקוע, גבעון החדשה, גבעת ברנר, גבעת זאב, גיזו, גני יוחנן, הראל, חולדה, טל שחר, יסודות, יציץ, כפר בן נון, כרמי יוסף, לטרון, מזכרת בתיה, מיני ישראל - נחשון, מסילת ציון, משמר דוד, נווה שלום, נחשון, נצר חזני, פדיה, צלפון, קריית עקרון, תעוז, בית חורון, כוכב יעקב, נטף, תל ציון, חוות חנינא, מגרון, רמת מגרון","alertDate":"2026-04-06T12:57:37.000Z","time":1775480257,"threat":0,"isDrill":false},{"data":"תל אביב - דרום העיר ויפו, תל אביב - מזרח, אור יהודה, אזור, בני ברק, בת ים, גבעת השלושה, גבעת שמואל, גבעתיים, גיבתון, גן שלמה, גת רימון, חולון, כפר סירקין, מעש, מקווה ישראל, נצר סרני, סביון, פארק אריאל שרון, פארק תעשיות פלמחים, פלמחים, פתח תקווה, קריית אונו, ראשון לציון - מזרח, ראשון לציון - מערב, רחובות, רמת גן - מזרח, רמת גן - מערב, גאליה, כפר הנגיד, אייל, אלישמע, ג'לג'וליה, גני עם, הוד השרון, חגור, חורשים, ירחיב, ירקונה, כפר ברא, מתן, נווה ימין, נווה ירק, עדנים, שדי חמד, אורנית, אירוס, בית חנן, בית עובד, גן שורק, גני תקווה, ישרש, כפר קאסם, מגשימים, נחלים, נטעים, נירית, נס ציונה, עיינות, עינת, ראש העין, תחנת רכבת ראש העין, אלפי מנשה, צופים, בית דגן, בית עוזיאל, גזר, גני הדר, חמד, כפר ביל''ו, כפר חב''ד, משמר איילון, משמר השבעה, נען, סתריה, פתחיה, צפריה, רמות מאיר, שערי תקווה, אזור תעשייה בראון, בית עלמין מורשה, סלעית, שבי שומרון, מסוף אורנית, חוות אלחי, מרכז אזורי דרום השרון, אזור תעשייה אפק ולב הארץ, גנות, דורות עילית","alertDate":"2026-04-06T12:57:34.000Z","time":1775480254,"threat":0,"isDrill":false},{"data":"גמזו, יהוד מונוסון, כפר דניאל, כפר רות, מבוא מודיעים, מודיעין - ליגד סנטר, מודיעין מכבים רעות, נוף איילון, שעלבים, שילת, אזור תעשייה נשר - רמלה, אחיסמך, אלעד, באר יעקב, בארות יצחק, בן שמן, בני עטרות, גבעת כ''ח, גינתון, כפר נוער בן שמן, לוד, מזור, מצליח, נופך, נחשונים, ניר צבי, רינתיה, רמלה, תעשיון צריפין, אזור תעשייה חבל מודיעין שוהם, אחיעזר, אלקנה, בית חשמונאי, בית נחמיה, בית עריף, ברקת, זיתן, חדיד, טירת יהודה, יגל, יד רמב''ם, כפר טרומן, כפר שמואל, נאות קדומים, עזריה, עץ אפרים, שוהם, חוות אביחי, פדואל, איירפורט סיטי, חוות צרידה, מודיעין - ישפרו סנטר","alertDate":"2026-04-06T12:57:32.000Z","time":1775480252,"threat":0,"isDrill":false},{"data":"חשמונאים, לפיד, מודיעין עילית, מתתיהו, בית אל, בית אריה, גבעת אסף, גלגל, דולב, טלמון, ייט''ב, יפית, כוכב השחר, נווה צוף, נחליאל, נילי, נעלה, נערן, נתיב הגדוד, עטרת, עפרה, פסגות, פצאל, רימונים, תומר, אעירה השחר, גופנה, החווה של זוהר, חוות מגנזי, חוות מעלה אהוביה, חוות נווה צוף, חוות עולם חסד, חוות ראש תאנה, חרשה, יבוא דודי, כפר האורנים, כרם רעים, מכינת אלישע, מלאכי השלום, נריה, עופרים, עינות קדם, שדה אפרים","alertDate":"2026-04-06T12:57:31.000Z","time":1775480251,"threat":0,"isDrill":false},{"data":"ברקן, חוות יאיר, יקיר, נופים, עמנואל, קריית נטפים, קרני שומרון, רבבה, אזור תעשייה אריאל, אזור תעשייה ברקן, איתמר, אלון מורה, ארגמן, בקעות, ברוכין, גבעת הראל, גיתית, הר ברכה, חוות גלעד, חמדת, חמרה, יצהר, כפר תפוח, מגדלים, מכורה, מעלה אפרים, מעלה לבונה, משואה, משכיות, עדי עד, עלי זהב - לשם, עלי, עמיחי, קדומים, קידה, רועי, רותם, רחלים, שבות רחל, שדמות מחולה, שילה, שלומציון, אביתר, אחיה, אריאל, אש קודש, בתרונות, גבעת הרואה, גבעת פורת יוסף, החווה של אורי כהן, החווה של יאיא, החווה של מנחם, החווה של עשהאל, חוות גנות, חוות הרשאש, חוות יד השומר, חוות מגדלים, חוות מרום שמואל, חוות נוף אב\"י, חוות נחל שילה, חוות פריאל, חוות שדה, חוות שוביאל, חוות שחרית, מצפור פצאל, נופי נחמיה","alertDate":"2026-04-06T12:57:25.000Z","time":1775480245,"threat":0,"isDrill":false},{"data":"סמר","alertDate":"2026-04-06T12:55:52.000Z","time":1775480152,"threat":5,"isDrill":false},{"data":"אליפז ומכרות תמנע","alertDate":"2026-04-06T12:54:12.000Z","time":1775480052,"threat":5,"isDrill":false},{"data":"באר אורה, מנרה, מרגליות","alertDate":"2026-04-06T12:54:09.000Z","time":1775480049,"threat":0,"isDrill":false},{"data":"ירושלים - אזור תעשייה עטרות, אזור תעשייה שער בנימין, כוכב יעקב, רימונים, תל ציון, חוות חנינא, חוות מעלה אהוביה, מגרון, רמת מגרון","alertDate":"2026-04-06T12:49:00.000Z","time":1775479740,"threat":0,"isDrill":false},{"data":"עפרה","alertDate":"2026-04-06T12:48:07.000Z","time":1775479687,"threat":0,"isDrill":false},{"data":"גבעת אסף","alertDate":"2026-04-06T12:48:00.000Z","time":1775479680,"threat":0,"isDrill":false},{"data":"ירושלים - כפר עקב, גבעון החדשה, גבעת זאב, משמר דוד, נווה שלום, נטף","alertDate":"2026-04-06T12:47:51.000Z","time":1775479671,"threat":0,"isDrill":false},{"data":"פסגות","alertDate":"2026-04-06T12:47:28.000Z","time":1775479648,"threat":0,"isDrill":false},{"data":"חרות, טירה, כפר הס, צור יצחק, תל מונד, אודים, בית יהושע, יקום, מכון וינגייט, תל יצחק, גבעת הראל, עלי, שילה, חוות נחל שילה","alertDate":"2026-04-06T12:47:26.000Z","time":1775479646,"threat":0,"isDrill":false},{"data":"כוכב יאיר - צור יגאל, רחלים","alertDate":"2026-04-06T12:47:08.000Z","time":1775479628,"threat":0,"isDrill":false},{"data":"משמרת, כפר תפוח, מעלה לבונה, נופי נחמיה, גבעת הרואה","alertDate":"2026-04-06T12:47:05.000Z","time":1775479625,"threat":0,"isDrill":false},{"data":"תל אביב - דרום העיר ויפו, תל אביב - מזרח, תל אביב - מרכז העיר, תל אביב - עבר הירקון, אור יהודה, אזור, בני ברק, בת ים, גבעת השלושה, גבעת חן, גבעת שמואל, גבעתיים, גת רימון, הרצליה - מערב, הרצליה - מרכז וגליל ים, חולון, יהוד מונוסון, כפר סירקין, כפר שמריהו, מעש, מקווה ישראל, סביון, פארק אריאל שרון, פתח תקווה, קריית אונו, ראשון לציון - מזרח, ראשון לציון - מערב, רמת גן - מזרח, רמת גן - מערב, רמת השרון, רעננה, גיבתון, גמזו, גן שלמה, חשמונאים, כפר דניאל, כפר רות, לפיד, מבוא חורון, מבוא מודיעים, מודיעין - ליגד סנטר, מודיעין מכבים רעות, מודיעין עילית, מתתיהו, נוף איילון, שעלבים, נצר סרני, פארק תעשיות פלמחים, פלמחים, רחובות, שילת, אורנית, אייל, אלישמע, אלעד, בארות יצחק, בית ברל, בני עטרות, ג'לג'וליה, גבעת כ''ח, גינתון, גן חיים, גני עם, גני תקווה, הוד השרון, חגור, חורשים, ירחיב, ירקונה, כפר ברא, כפר מל''ל, כפר נוער בן שמן, כפר סבא, כפר קאסם, מגשימים, מזור, מתן, נווה ימין, נווה ירק, נופך, נחלים, נחשונים, ניר אליהו, נירית, עדנים, עינת, צופית, ראש העין, רינתיה, רמות השבים, רמת הכובש, שדה ורבורג, שדי חמד, תחנת רכבת ראש העין, בית אלעזרי, גאליה, יבנה, כפר הנגיד, אזור תעשייה נשר - רמלה, אחיסמך, אירוס, באר יעקב, בית חנן, בית עובד, בן שמן, גן שורק, ישרש, לוד, מצליח, נטעים, ניר צבי, נס ציונה, עיינות, רמלה, תעשיון צריפין, אזור תעשייה חבל מודיעין שוהם, אחיעזר, אלפי מנשה, אלקנה, ארסוף, בית דגן, בית נחמיה, בית עריף, בני ציון, בצרה, ברקן, ברקת, געש, זיתן, חדיד, חוות יאיר, חמד, חרוצים, טירת יהודה, יגל, יקיר, כפר חב''ד, כפר טרומן, משמר השבעה, נופים, עמנואל, עץ אפרים, צופים, צפריה, קריית נטפים, קרני שומרון, רבבה, רשפון, שוהם, שערי תקווה, שפיים, בית גמליאל, בן זכאי, בניה, בית חשמונאי, בית עוזיאל, בקוע, גבעת ברנר, גזר, גני הדר, גני יוחנן, חולדה, יד רמב''ם, יציץ, כפר ביל''ו, כפר בן נון, כפר שמואל, כרמי יוסף, לטרון, מזכרת בתיה, מיני ישראל - נחשון, משמר איילון, נאות קדומים, נחשון, נען, סתריה, עזריה, פדיה, פתחיה, קריית עקרון, רמות מאיר, אזור תעשייה אריאל, אזור תעשייה ברקן, בית אריה, בית עלמין מורשה, ברוכין, חוות אביחי, מסוף אורנית, נווה צוף, עטרת, עלי זהב - לשם, פדואל, מעון צופיה, בית אל, בית חורון, דולב, טלמון, נחליאל, נילי, נעלה, אזור תעשייה אפק ולב הארץ, איירפורט סיטי, אריאל, גנות, דורות עילית, חוות נווה צוף, חוות נוף אב\"י, חוות עולם חסד, חוות צרידה, חוות שוביאל, חוות שחרית, מכינת אלישע, מרכז אזורי דרום השרון, מתחם גלילות, מתחם פי גלילות, עופרים, גופנה, חוות מגנזי, חרשה, יבוא דודי, כפר האורנים, כרם רעים, מודיעין - ישפרו סנטר, נריה, שדה אפרים","alertDate":"2026-04-06T12:46:59.000Z","time":1775479619,"threat":0,"isDrill":false},{"data":"אזור תעשייה שחורת","alertDate":"2026-04-06T12:32:16.000Z","time":1775478736,"threat":5,"isDrill":false}]